intermix.py
intermix-0.6.dist-info/RECORD
intermix-0.6.dist-info/metadata.json
intermix-0.6.dist-info/WHEEL
intermix-0.6.dist-info/DESCRIPTION.rst
intermix-0.6.dist-info/top_level.txt
intermix-0.6.dist-info/LICENSE.txt
intermix-0.6.dist-info/METADATA
