Metadata-Version: 2.0
Name: intermix
Version: 0.6
Summary: Plugin to add Intermix annotations to SQL queries
Home-page: http://docs.intermix.io/plugins
Author: Intermix Software
Author-email: contact@intermix.io
License: MIT License
Platform: UNKNOWN
Classifier: Development Status :: 4 - Beta
Classifier: Environment :: Plugins
Classifier: Intended Audience :: Developers
Classifier: Intended Audience :: System Administrators
Classifier: License :: OSI Approved :: MIT License
Classifier: Programming Language :: Python :: 2.7
Classifier: Programming Language :: Python :: 3.4
Classifier: Programming Language :: Python :: 3.5
Classifier: Programming Language :: Python :: 3.6
Classifier: Topic :: System :: Monitoring
